hacku/__init__.py
hacku/crypto.py
hacku/file.py
hacku/ip.db
hacku/ip2region.py
hacku/mongo.py
hacku/net.py
hacku/nps.py
hacku/oneapi.py
hacku/pii.py
hacku/proxy.py
hacku/s5pp.py
hacku/search.py
hacku/utils.py
hacku-1.7.9.dist-info/entry_points.txt
hacku-1.7.9.dist-info/LICENSE
hacku-1.7.9.dist-info/METADATA
hacku-1.7.9.dist-info/WHEEL
hacku-1.7.9.dist-info/RECORD
